[{"name":"","url":"http:\/\/transponder.petervanderlaan.nl\/tv.m3u","label":"4 {1}","type":"group","logo":"fa-shopping-bag","entries":[]},{"name":"","url":"http:\/\/m3u.cl\/playlist\/total.m3u","label":"4 {1}","type":"group","logo":"fa-shopping-bag","entries":[]},{"name":"","url":"http:\/\/cartatv.es:8080\/playlist\/UeYFU3bduW\/24nYjH8eMe\/m3u_plus","label":"3 {1}","type":"group","logo":"fa-shopping-bag","entries":[]},{"name":"","url":"http:\/\/4663893855151056:4663893855151056@ott-protv.com:8080#xtream","label":"3 {1}","type":"group","logo":"fa-shopping-bag","entries":[]},{"name":"","url":"https:\/\/github.com\/Free-TV\/IPTV\/raw\/master\/playlists\/playlist_venezuela.m3u8","label":"3 {1}","type":"group","logo":"fa-shopping-bag","entries":[]},{"name":"","url":"https:\/\/github.com\/Free-TV\/IPTV\/raw\/master\/playlists\/playlist_chile.m3u8","label":"2 {1}","type":"group","logo":"fa-shopping-bag","entries":[]},{"name":"","url":"https:\/\/github.com\/Free-TV\/IPTV\/raw\/master\/playlists\/playlist_mexico.m3u8","label":"2 {1}","type":"group","logo":"fa-shopping-bag","entries":[]},{"name":"","url":"http:\/\/tvpremiumhd.club\/lista.m3u","label":"2 {1}","type":"group","logo":"fa-shopping-bag","entries":[]},{"name":"","url":"https:\/\/github.com\/Free-TV\/IPTV\/raw\/master\/playlists\/playlist_costa_rica.m3u8","label":"2 {1}","type":"group","logo":"fa-shopping-bag","entries":[]},{"name":"","url":"https:\/\/ift.tt\/2pKZ6ym","label":"2 {1}","type":"group","logo":"fa-shopping-bag","entries":[]},{"name":"","url":"http:\/\/tvpremiumhd.club\/tv.m3u","label":"2 {1}","type":"group","logo":"fa-shopping-bag","entries":[]},{"name":"","url":"https:\/\/iptv-org.github.io\/iptv\/countries\/ve.m3u","label":"2 {1}","type":"group","logo":"fa-shopping-bag","entries":[]},{"name":"","url":"https:\/\/iptv-org.github.io\/iptv\/countries\/us.m3u","label":"2 {1}","type":"group","logo":"fa-shopping-bag","entries":[]},{"name":"","url":"https:\/\/raw.githubusercontent.com\/helenfernanda\/gratis\/main\/iptvlegal.m3u","label":"2 {1}","type":"group","logo":"fa-shopping-bag","entries":[]},{"name":"","url":"http:\/\/bit.ly\/andentv44","label":"2 {1}","type":"group","logo":"fa-shopping-bag","entries":[]},{"name":"","url":"http:\/\/tv.teleclub.xyz\/lista\/canales.m3u","label":"1 {0}","type":"group","logo":"fa-shopping-bag","entries":[]},{"name":"","url":"https:\/\/github.com\/Free-TV\/IPTV\/raw\/master\/playlists\/playlist_zz_news_es.m3u8","label":"1 {0}","type":"group","logo":"fa-shopping-bag","entries":[]},{"name":"","url":"https:\/\/rebrand.ly\/fdxtz8ry26drdc6","label":"1 {0}","type":"group","logo":"fa-shopping-bag","entries":[]},{"name":"","url":"https:\/\/bit.ly\/3p1v4SA.","label":"1 {0}","type":"group","logo":"fa-shopping-bag","entries":[]},{"name":"","url":"https:\/\/github.com\/Free-TV\/IPTV\/raw\/master\/playlists\/playlist_zz_news_ar.m3u8","label":"1 {0}","type":"group","logo":"fa-shopping-bag","entries":[]},{"name":"","url":"http:\/\/47114.sportiumvip.xyz:8080\/playlist\/TV-29553503\/369298012875\/m3u_plus","label":"1 {0}","type":"group","logo":"fa-shopping-bag","entries":[]},{"name":"","url":"https:\/\/gist.githubusercontent.com\/card2006\/04bb99a18393885681077840b933952b\/raw\/d1998a8b4bfa4c8d6195444e4902ef6aad62f233\/TIRI%2520MARRANO%2520SOLO%2520ADULTOS%2520+18%2520M3U","label":"1 {0}","type":"group","logo":"fa-shopping-bag","entries":[]}]